swiftpath/__init__.py
swiftpath/swiftpath.py
swiftpath-0.0.1.dev0.dist-info/LICENSE
swiftpath-0.0.1.dev0.dist-info/METADATA
swiftpath-0.0.1.dev0.dist-info/WHEEL
swiftpath-0.0.1.dev0.dist-info/top_level.txt
swiftpath-0.0.1.dev0.dist-info/zip-safe
swiftpath-0.0.1.dev0.dist-info/RECORD
