Metadata-Version: 2.1
Name: swiftpath
Version: 0.0.1.dev0
Summary: A pathlib-derived interface to Openstack Swift
Home-page: https://github.com/canonical/swiftpath
Author: Dan Ryan
Author-email: dan.ryan@canonical.com
License: Apache-2.0
Project-URL: Source Code, https://github.com/canonical/swiftpath
Project-URL: Change Log, https://github.com/canonical/swiftpath/CHANGES.rst
Keywords: swift pathlib openstack object storage
Platform: UNKNOWN
Classifier: Development Status :: 4 - Beta
Classifier: License :: OSI Approved :: Apache Software License
Classifier: Operating System :: OS Independent
Classifier: Programming Language :: Python :: 3
Classifier: Programming Language :: Python :: 3.6
Classifier: Programming Language :: Python :: 3.7
Classifier: Programming Language :: Python :: 3.8
Classifier: Topic :: Software Development :: Libraries :: Python Modules
Requires-Python: >=3.6
Requires-Dist: keystoneauth1
Requires-Dist: openstackclient
Requires-Dist: python-swiftclient
Provides-Extra: dev
Requires-Dist: invoke ; extra == 'dev'
Requires-Dist: pre-commit ; extra == 'dev'
Requires-Dist: rope ; extra == 'dev'
Requires-Dist: sphinx-rtd-theme ; extra == 'dev'
Requires-Dist: sphinx-autodoc-typehints ; extra == 'dev'
Provides-Extra: lint
Requires-Dist: black ; extra == 'lint'
Requires-Dist: flake8 ; extra == 'lint'
Requires-Dist: flake8-bugbear ; extra == 'lint'
Requires-Dist: isort ; extra == 'lint'
Requires-Dist: mypy ; extra == 'lint'
Provides-Extra: release
Requires-Dist: parver ; extra == 'release'
Requires-Dist: towncrier ; extra == 'release'
Provides-Extra: tests
Requires-Dist: coverage ; extra == 'tests'
Requires-Dist: pytest ; extra == 'tests'
Requires-Dist: pytest-timeout ; extra == 'tests'
Requires-Dist: readme-renderer[md] ; extra == 'tests'
Requires-Dist: twine ; extra == 'tests'
Requires-Dist: swiftmock ; extra == 'tests'
